trustworthyai_text/__init__.py
trustworthyai_text/version.py
trustworthyai_text/common/__init__.py
trustworthyai_text/common/constants.py
trustworthyai_text/managers/__init__.py
trustworthyai_text/managers/error_analysis_manager.py
trustworthyai_text/managers/explainer_manager.py
trustworthyai_text/tai_text_insights/__init__.py
trustworthyai_text/tai_text_insights/tai_text_insights.py
trustworthyai_text/utils/__init__.py
trustworthyai_text/utils/feature_extractors.py
trustworthyai_text/utils/question_answering.py
trustworthyai_text/utils/genai_metrics/__init__.py
trustworthyai_text/utils/genai_metrics/constants.py
trustworthyai_text/utils/genai_metrics/metrics.py
trustworthyai_text/utils/genai_metrics/scripts/__init__.py
trustworthyai_text/utils/genai_metrics/scripts/_compute.py
trustworthyai_text/utils/genai_metrics/scripts/coherence.py
trustworthyai_text/utils/genai_metrics/scripts/equivalence.py
trustworthyai_text/utils/genai_metrics/scripts/fluency.py
trustworthyai_text/utils/genai_metrics/scripts/groundedness.py
trustworthyai_text/utils/genai_metrics/scripts/relevance.py
trustworthyai_text-0.2.12.dist-info/METADATA
trustworthyai_text-0.2.12.dist-info/WHEEL
trustworthyai_text-0.2.12.dist-info/top_level.txt
trustworthyai_text-0.2.12.dist-info/RECORD
