Metadata-Version: 2.1
Name: trustworthyai_text
Version: 0.2.12
Summary: SDK API to assess text Machine Learning models.
Home-page: https://github.com/affectlog/trustworthy-ai-toolbox
Author: AL360°
Author-email: developer@affectlog.com
Classifier: Programming Language :: Python :: 3.7
Classifier: Programming Language :: Python :: 3.8
Classifier: Programming Language :: Python :: 3.9
Classifier: License :: OSI Approved :: MIT License
Classifier: Operating System :: OS Independent
Classifier: Development Status :: 3 - Alpha
Requires-Python: >=3.7
Requires-Dist: numpy<2.0.0,>=1.17.2
Requires-Dist: pyarrow>=12.0.0
Requires-Dist: pandas>=0.25.1
Requires-Dist: scikit-learn>=0.22.1
Requires-Dist: scipy>=1.4.1
Requires-Dist: semver~=2.13.0
Requires-Dist: affectlog-feature-extractors==0.1.0
Requires-Dist: trustworthyai==0.0.0
Provides-Extra: generative_text
Requires-Dist: interpret-text; extra == "generative-text"
Requires-Dist: sentence-transformers; extra == "generative-text"
Provides-Extra: qa
Requires-Dist: evaluate; extra == "qa"
Requires-Dist: bert-score; extra == "qa"
Requires-Dist: nltk; extra == "qa"
Requires-Dist: rouge-score; extra == "qa"
